{"cameraMode":{"drawMode":0,"name":"Shaded","section":"Shading Mode"},"sceneLighting":false,"audioPlay":false,"sceneViewState":{"m_AlwaysRefresh":false,"showFog":true,"showSkybox":true,"showFlares":true,"showImageEffects":true,"showParticleSystems":true,"showVisualEffectGraphs":true,"m_FxEnabled":true},"in2DMode":false,"pivot":{"x":795.80419921875,"y":171.35079956054688,"z":590.9163818359375},"rotation":{"x":-0.05903695523738861,"y":-0.10728496313095093,"z":0.006292335689067841,"w":-0.9925470948219299},"size":814.8189086914063,"orthographic":false}